{
    "title": "Tuer sans etat d'ame",
    "synopsis": "Après sa première bataille contre un ennemi insaisissable, un soldat commence à éprouver des sensations inhabituelles et à rencontrer d'étranges problèmes techniques.",
    "director": "Jakob Verbruggen",
    "writtor": "Charlie Brooker",
    "casting": [{
            "name": "Malachi Kirby"
        },
        {
            "name": "Madeline Brewer"
        },
        {
            "name": "Michael Kelly"
        },
        {
            "name": "Sarah Snook"
        }
    ],
    "critics": [{
            "name": "Yannick Nana",
            "comments": "Add smthg "
        },
        {
            "name": "Daily Mirror(UK)",
            "comments": "... it's an episode that rewards knowledge of earlier Black Mirror episodes, and forces you to think about the philosophical consequences of high-tech warfare. "
        }
    ],
    "ratings": " &#9733;&#9733;&#9733;&#9733;&#9733;&#9733;&#9734;&#9734;&#9734;&#9734;"
}